mailcalaid/__init__.py
mailcalaid/common.py
mailcalaid/mail2bot.py
mailcalaid/mailaid.py
mailcalaid/cal/__init__.py
mailcalaid/cal/holiday.py
mailcalaid/mail/__init__.py
mailcalaid/mail/imapclient.py
mailcalaid/mail/mailclient.py
mailcalaid/mail/pop3client.py
mailcalaid-1.0.2.dist-info/LICENSE
mailcalaid-1.0.2.dist-info/METADATA
mailcalaid-1.0.2.dist-info/WHEEL
mailcalaid-1.0.2.dist-info/top_level.txt
mailcalaid-1.0.2.dist-info/RECORD
