Metadata-Version: 2.1
Name: mailcalaid
Version: 1.0.2
Summary: Start selling to enterprise customers with just a few lines of code.
Author-email: Klesh Wong <klesh@qq.com>
Project-URL: Documentation, https://mailcalaid.readthedocs.io/en/latest/
Project-URL: Source Code, https://github.com/klesh/mailcalaid
Project-URL: Issue Tracker, https://github.com/klesh/mailcalaid/issues
Classifier: Environment :: Console
Classifier: Intended Audience :: Developers
Classifier: License :: OSI Approved :: MIT License
Classifier: Operating System :: Microsoft :: Windows
Classifier: Operating System :: POSIX :: Linux
Classifier: Operating System :: Unix
Classifier: Operating System :: MacOS
Classifier: Operating System :: POSIX :: BSD
Requires-Python: >=3.8
License-File: LICENSE
